LICENSE
object_detector/__init__.py
object_detector/data/coco.names
object_detector/data/yolo_colors.txt
object_detector/data/yolov2-tiny.cfg
object_detector/data/yolov2-tiny.weights
object_detector/scan_buffer.py
object_detector/scan_file.py
object_detector/scan_filelist.py
object_detector/settings.py
object_detector/yolo/__init__.py
object_detector/yolo/yolo_detector.py
python_object_detector-0.1.1.dist-info/LICENSE
python_object_detector-0.1.1.dist-info/WHEEL
python_object_detector-0.1.1.dist-info/METADATA
python_object_detector-0.1.1.dist-info/RECORD
